dm_sonnet_gpu-1.32.dist-info/DESCRIPTION.rst
dm_sonnet_gpu-1.32.dist-info/METADATA
dm_sonnet_gpu-1.32.dist-info/RECORD
dm_sonnet_gpu-1.32.dist-info/WHEEL
dm_sonnet_gpu-1.32.dist-info/metadata.json
dm_sonnet_gpu-1.32.dist-info/top_level.txt
sonnet/__init__.py
