Metadata-Version: 2.0
Name: dm-sonnet-gpu
Version: 1.32
Summary: Sonnet is a library for building neural networks in TensorFlow.
Home-page: https://github.com/deepmind/sonnet
Author: DeepMind
Author-email: sonnet-dev-os@google.com
License: Apache 2.0
Keywords: sonnet tensorflow tensor machine learning
Platform: UNKNOWN
Classifier: Development Status :: 4 - Beta
Classifier: Intended Audience :: Developers
Classifier: Intended Audience :: Education
Classifier: Intended Audience :: Science/Research
Classifier: License :: OSI Approved :: Apache Software License
Classifier: Programming Language :: Python :: 2.7
Classifier: Topic :: Scientific/Engineering :: Mathematics
Classifier: Topic :: Software Development :: Libraries :: Python Modules
Classifier: Topic :: Software Development :: Libraries
